curlify3/__init__.py
curlify3/_base.py
curlify3/_curl.py
curlify3/_req_aiohttp.py
curlify3/_req_httpx.py
curlify3/_req_requests.py
curlify3/_req_starlette.py
curlify3/_utils.py
curlify3-0.5.dist-info/METADATA
curlify3-0.5.dist-info/WHEEL
curlify3-0.5.dist-info/RECORD
