Metadata-Version: 2.1
Name: curlify3
Version: 0.5
Summary: yet another library to convert request object to curl command
Home-page: https://github.com/shpaker/curlify3
Author: A.Shpak
Author-email: aleksander.shpak.als@gmail.com
Requires-Python: >=3.8
Classifier: Programming Language :: Python :: 3
Classifier: Programming Language :: Python :: 3.8
Classifier: Programming Language :: Python :: 3.9
Classifier: Programming Language :: Python :: 3.10
Classifier: Programming Language :: Python :: 3.11
Classifier: Programming Language :: Python :: 3.12
Classifier: Programming Language :: Python :: 3.13
Project-URL: Repository, https://github.com/shpaker/curlify3
